NiukeShangyeChanpinXiaozhaoQiuzhiGonglve20212022Fix1/README.md
NiukeShangyeChanpinXiaozhaoQiuzhiGonglve20212022Fix1/__init__.py
NiukeShangyeChanpinXiaozhaoQiuzhiGonglve20212022Fix1/__main__.py
NiukeShangyeChanpinXiaozhaoQiuzhiGonglve20212022Fix1/file.epub
NiukeShangyeChanpinXiaozhaoQiuzhiGonglve20212022Fix1/index.html
NiukeShangyeChanpinXiaozhaoQiuzhiGonglve20212022Fix1/css/__init__.py
NiukeShangyeChanpinXiaozhaoQiuzhiGonglve20212022Fix1/css/annotations.css
NiukeShangyeChanpinXiaozhaoQiuzhiGonglve20212022Fix1/css/main.css
NiukeShangyeChanpinXiaozhaoQiuzhiGonglve20212022Fix1/css/normalize.css
NiukeShangyeChanpinXiaozhaoQiuzhiGonglve20212022Fix1/css/popup.css
NiukeShangyeChanpinXiaozhaoQiuzhiGonglve20212022Fix1/font/__init__.py
NiukeShangyeChanpinXiaozhaoQiuzhiGonglve20212022Fix1/font/fontello.eot
NiukeShangyeChanpinXiaozhaoQiuzhiGonglve20212022Fix1/font/fontello.svg
NiukeShangyeChanpinXiaozhaoQiuzhiGonglve20212022Fix1/font/fontello.ttf
NiukeShangyeChanpinXiaozhaoQiuzhiGonglve20212022Fix1/font/fontello.woff
NiukeShangyeChanpinXiaozhaoQiuzhiGonglve20212022Fix1/img/__init__.py
NiukeShangyeChanpinXiaozhaoQiuzhiGonglve20212022Fix1/img/annotator-glyph-sprite.png
NiukeShangyeChanpinXiaozhaoQiuzhiGonglve20212022Fix1/img/annotator-icon-sprite.png
NiukeShangyeChanpinXiaozhaoQiuzhiGonglve20212022Fix1/img/apple-touch-icon.png
NiukeShangyeChanpinXiaozhaoQiuzhiGonglve20212022Fix1/img/cancelfullscreen.png
NiukeShangyeChanpinXiaozhaoQiuzhiGonglve20212022Fix1/img/close.png
NiukeShangyeChanpinXiaozhaoQiuzhiGonglve20212022Fix1/img/fullscreen.png
NiukeShangyeChanpinXiaozhaoQiuzhiGonglve20212022Fix1/img/loader.gif
NiukeShangyeChanpinXiaozhaoQiuzhiGonglve20212022Fix1/img/menu-icon.png
NiukeShangyeChanpinXiaozhaoQiuzhiGonglve20212022Fix1/img/save.png
NiukeShangyeChanpinXiaozhaoQiuzhiGonglve20212022Fix1/img/saved.png
NiukeShangyeChanpinXiaozhaoQiuzhiGonglve20212022Fix1/img/settings-s.png
NiukeShangyeChanpinXiaozhaoQiuzhiGonglve20212022Fix1/img/settings.png
niuke_shangye_chanpin_xiaozhao_qiuzhi_gonglve_2021_2022_fix1-2025.3.25.1.dist-info/METADATA
niuke_shangye_chanpin_xiaozhao_qiuzhi_gonglve_2021_2022_fix1-2025.3.25.1.dist-info/WHEEL
niuke_shangye_chanpin_xiaozhao_qiuzhi_gonglve_2021_2022_fix1-2025.3.25.1.dist-info/entry_points.txt
niuke_shangye_chanpin_xiaozhao_qiuzhi_gonglve_2021_2022_fix1-2025.3.25.1.dist-info/top_level.txt
niuke_shangye_chanpin_xiaozhao_qiuzhi_gonglve_2021_2022_fix1-2025.3.25.1.dist-info/RECORD
